scoops/__init__.py
scoops-0.0.1.dist-info/licenses/LICENSE
scoops-0.0.1.dist-info/METADATA
scoops-0.0.1.dist-info/WHEEL
scoops-0.0.1.dist-info/top_level.txt
scoops-0.0.1.dist-info/RECORD
